bnlearn/__init__.py
bnlearn/bnlearn.py
bnlearn/confmatrix.py
bnlearn/discretize.py
bnlearn/examples.py
bnlearn/examples_discretize.py
bnlearn/impute.py
bnlearn/inference.py
bnlearn/learn_discrete_bayes_net.py
bnlearn/network.py
bnlearn/parameter_learning.py
bnlearn/sampling.py
bnlearn/structure_learning.py
bnlearn-0.12.2.dist-info/licenses/LICENSE
bnlearn-0.12.2.dist-info/METADATA
bnlearn-0.12.2.dist-info/WHEEL
bnlearn-0.12.2.dist-info/top_level.txt
bnlearn-0.12.2.dist-info/RECORD
