Metadata-Version: 2.4
Name: bnlearn
Version: 0.12.2
Summary: bnlearn is a Python package for Causal Discovery by learning the graphical structure of Bayesian networks, parameter learning, inference and sampling methods.
Author-email: Erdogan Taskesen <erdogant@gmail.com>
License-Expression: MIT
Project-URL: Homepage, https://erdogant.github.io/bnlearn
Project-URL: Download, https://github.com/erdogant/bnlearn/archive/{version}.tar.gz
Keywords: Python,causal discovery,causal learning
Classifier: Programming Language :: Python :: 3
Classifier: Operating System :: OS Independent
Classifier: Intended Audience :: Education
Classifier: Intended Audience :: Science/Research
Classifier: Operating System :: Unix
Classifier: Operating System :: Microsoft :: Windows
Classifier: Operating System :: MacOS
Classifier: Topic :: Scientific/Engineering :: Artificial Intelligence
Requires-Python: >=3
License-File: LICENSE
Requires-Dist: pgmpy==0.1.25
Requires-Dist: networkx>=2.7.1
Requires-Dist: matplotlib>=3.3.4
Requires-Dist: numpy>=1.24.1
Requires-Dist: pandas
Requires-Dist: tqdm
Requires-Dist: ismember
Requires-Dist: scikit-learn
Requires-Dist: funcsigs
Requires-Dist: statsmodels
Requires-Dist: python-louvain
Requires-Dist: packaging
Requires-Dist: df2onehot
Requires-Dist: fsspec
Requires-Dist: pypickle
Requires-Dist: tabulate
Requires-Dist: ipywidgets
Requires-Dist: datazets>=1.1.2
Requires-Dist: setgraphviz>=1.0.3
Requires-Dist: lingam
Dynamic: license-file
